setup.py
statistics_distributions_bg/Binomialdistribution.py
statistics_distributions_bg/Gaussiandistribution.py
statistics_distributions_bg/Generaldistribution.py
statistics_distributions_bg/__init__.py
statistics_distributions_bg.egg-info/PKG-INFO
statistics_distributions_bg.egg-info/SOURCES.txt
statistics_distributions_bg.egg-info/dependency_links.txt
statistics_distributions_bg.egg-info/not-zip-safe
statistics_distributions_bg.egg-info/top_level.txt