Metadata-Version: 1.0
Name: statistics-distributions-bg
Version: 0.1
Summary: Gaussian and binomial distributions
Home-page: UNKNOWN
Author: UNKNOWN
Author-email: UNKNOWN
License: UNKNOWN
Platform: UNKNOWN
